{"row_names": ["tab0_chinese", "tab0_filipino", "tab0_indian", "tab0_white", "tab0_indonesian", "tab0_korean", "tab0_others"], "meta": {"table_name": "Ethnicity", "table_names": {"S": "\u79cd\u65cf", "E": "Ethnicity", "T": "\u7a2e\u65cf"}, "table_id": 0, "area": "T04"}, "data": [["", 6643.0, 7702.0, 14345.0], ["", 266.0, 953.0, 1219.0], ["", 432.0, 532.0, 964.0], ["", 621.0, 248.0, 869.0], ["", 17.0, 537.0, 554.0], ["", 154.0, 166.0, 320.0], ["", 409.0, 448.0, 857.0]], "column_names": ["tab0_ethnicity", "tab0_none", "tab0_male", "tab0_female", "tab0_both"]}