{"row_names": ["a19_cantonese", "a20_putonghua", "a21_other", "a22_english", "a23_others", "a24_persons"], "meta": {"table_name": "Usual Language", "table_names": {"S": "\u60ef\u7528\u8bed\u8a00", "E": "Usual Language", "T": "\u6163\u7528\u8a9e\u8a00"}, "table_id": 1, "area": "P16"}, "data": [["", 6802.0, 7429.0, 14231.0], ["", 54.0, 243.0, 297.0], ["", 36.0, 82.0, 118.0], ["", 43.0, 126.0, 169.0], ["", 0.0, 130.0, 130.0], ["", 370.0, 360.0, 730.0]], "column_names": ["a18_usual", "b18_none", "c18_male", "d18_female", "e18_both"]}