{"row_names": ["a19_cantonese", "a20_putonghua", "a21_other", "a22_english", "a23_others", "a24_persons"], "meta": {"table_name": "Usual Language", "table_names": {"S": "\u60ef\u7528\u8bed\u8a00", "E": "Usual Language", "T": "\u6163\u7528\u8a9e\u8a00"}, "table_id": 1, "area": "A05"}, "data": [["", 5848.0, 7068.0, 12916.0], ["", 242.0, 307.0, 549.0], ["", 52.0, 84.0, 136.0], ["", 1370.0, 2956.0, 4326.0], ["", 199.0, 439.0, 638.0], ["", 472.0, 460.0, 932.0]], "column_names": ["a18_usual", "b18_none", "c18_male", "d18_female", "e18_both"]}