{"row_names": ["h119_<", "h120_2000", "h121_4000", "h122_6000", "h123_8000", "h124_10000", "h125_15000", "h126_20000", "h127_25000", "h128_30000", "h129_40000", "h130_60000", "h131_80000", "h132_>="], "meta": {"table_name": "Monthly Domestic Household Income", "table_names": {"S": "\u5bb6\u5ead\u4f4f\u6237\u6bcf\u6708\u6536\u5165\uff08\u6e2f\u5143\uff09", "E": "Monthly Domestic Household Income (HK$)", "T": "\u5bb6\u5ead\u4f4f\u6236\u6bcf\u6708\u6536\u5165\uff08\u6e2f\u5143\uff09"}, "table_id": 18, "area": "C22"}, "data": [["", "", "", 45.0, "", 432.0], ["", "", "", 21.0, "", 134.0], ["", "", "", 36.0, "", 168.0], ["", "", "", 76.0, "", 180.0], ["", "", "", 115.0, "", 154.0], ["", "", "", 540.0, "", 570.0], ["", "", "", 397.0, "", 441.0], ["", "", "", 452.0, "", 489.0], ["", "", "", 370.0, "", 395.0], ["", "", "", 665.0, "", 713.0], ["", "", "", 900.0, "", 1090.0], ["", "", "", 419.0, "", 425.0], ["", "", "", 181.0, "", 181.0], ["", "", "", 218.0, "", 224.0]], "column_names": ["h118_household", "i118_none", "j118_none", "k118_none", "l118_active", "m118_none", "n118_households"]}