{"row_names": ["h62_in", "h63_in", "h64_hong", "h65_kowloon", "h66_new", "h67_other", "h68_no", "h69_work", "h70_places"], "meta": {"table_name": "Place of Work", "table_names": {"S": "\u5de5\u4f5c\u5730\u70b9", "E": "Place of Work", "T": "\u5de5\u4f5c\u5730\u9ede"}, "table_id": 15, "area": "D13"}, "data": [["", "", "", 1188.0, 1374.0, 2562.0], ["", "", "", "", "", ""], ["", "", "", 1542.0, 1321.0, 2863.0], ["", "", "", 618.0, 567.0, 1185.0], ["", "", "", 323.0, 224.0, 547.0], ["", "", "", 113.0, 29.0, 142.0], ["", "", "", 644.0, 239.0, 883.0], ["", "", "", 54.0, 202.0, 256.0], ["", "", "", 83.0, 25.0, 108.0]], "column_names": ["h61_place", "i61_none", "j61_none", "k61_none", "l61_male", "m61_female", "n61_both"]}