{"row_names": ["a29_never", "a30_now", "a31_widowed", "a32_divorced", "a33_separated", "a34_persons"], "meta": {"table_name": "Marital Status", "table_names": {"S": "\u5a5a\u59fb\u72b6\u51b5", "E": "Marital Status", "T": "\u5a5a\u59fb\u72c0\u6cc1"}, "table_id": 2, "area": "K06"}, "data": [["", 1906.0, 2400.0, 4306.0], ["", 4734.0, 5321.0, 10055.0], ["", 47.0, 541.0, 588.0], ["", 76.0, 304.0, 380.0], ["", 16.0, 69.0, 85.0], ["", 1319.0, 1324.0, 2643.0]], "column_names": ["a28_marital", "b28_none", "c28_male", "d28_female", "e28_both"]}