{"row_names": ["h96_manufacturing", "h97_construction", "h98_importexport", "h99_transportation", "h100_accommodation", "h101_information", "h102_financing", "h103_real", "h104_public", "h105_health", "h106_miscellaneous", "h107_others"], "meta": {"table_name": "Industry", "table_names": {"S": "\u884c\u4e1a", "E": "Industry", "T": "\u884c\u696d"}, "table_id": 17, "area": "G09"}, "data": [["", "", "", 270.0, 189.0, 459.0], ["", "", "", 204.0, 71.0, 275.0], ["", "", "", 1176.0, 969.0, 2145.0], ["", "", "", 93.0, 66.0, 159.0], ["", "", "", 85.0, 59.0, 144.0], ["", "", "", 239.0, 113.0, 352.0], ["", "", "", 446.0, 349.0, 795.0], ["", "", "", 433.0, 540.0, 973.0], ["", "", "", 909.0, 713.0, 1622.0], ["", "", "", "", "", ""], ["", "", "", 156.0, 2917.0, 3073.0], ["", "", "", 34.0, 13.0, 47.0]], "column_names": ["h95_industry", "i95_none", "j95_none", "k95_none", "l95_male", "m95_female", "n95_both"]}