{"row_names": ["a62_working", "a63_employees", "a64_employers", "a65_self-employed", "a66_unpaid", "a67_persons", "a68_home-makers", "a69_students", "a70_retired", "a71_others"], "meta": {"table_name": "Economic Activity Status", "table_names": {"S": "\u7ecf\u6d4e\u6d3b\u52a8\u8eab\u5206", "E": "Economic Activity Status", "T": "\u7d93\u6fdf\u6d3b\u52d5\u8eab\u5206"}, "table_id": 4, "area": "J10"}, "data": [["", "", "", ""], ["", 2738.0, 2622.0, 5360.0], ["", 39.0, 0.0, 39.0], ["", 258.0, 73.0, 331.0], ["", 0.0, 0.0, 0.0], ["", "", "", ""], ["", 82.0, 1009.0, 1091.0], ["", 760.0, 719.0, 1479.0], ["", 1583.0, 1626.0, 3209.0], ["", 1030.0, 1238.0, 2268.0]], "column_names": ["a61_economic", "b61_none", "c61_male", "d61_female", "e61_both"]}