{"row_names": ["h82_managers", "h83_professionals", "h84_associate", "h85_clerical", "h86_service", "h87_craft", "h88_plant", "h89_elementary", "h90_skilled", "h91_occupations"], "meta": {"table_name": "Occupation", "table_names": {"S": "\u804c\u4e1a", "E": "Occupation", "T": "\u8077\u696d"}, "table_id": 16, "area": "S26"}, "data": [["", "", "", 477.0, 327.0, 804.0], ["", "", "", 424.0, 184.0, 608.0], ["", "", "", 841.0, 845.0, 1686.0], ["", "", "", 431.0, 790.0, 1221.0], ["", "", "", 919.0, 906.0, 1825.0], ["", "", "", 776.0, 58.0, 834.0], ["", "", "", 415.0, 39.0, 454.0], ["", "", "", 796.0, 1372.0, 2168.0], ["", "", "", 0.0, 0.0, 0.0], ["", "", "", "", "", ""]], "column_names": ["h81_occupation", "i81_none", "j81_none", "k81_none", "l81_male", "m81_female", "n81_both"]}