{"row_names": ["a19_cantonese", "a20_putonghua", "a21_other", "a22_english", "a23_others", "a24_persons"], "meta": {"table_name": "Usual Language", "table_names": {"S": "\u60ef\u7528\u8bed\u8a00", "E": "Usual Language", "T": "\u6163\u7528\u8a9e\u8a00"}, "table_id": 1, "area": "S26"}, "data": [["", 7898.0, 8601.0, 16499.0], ["", 239.0, 155.0, 394.0], ["", 700.0, 634.0, 1334.0], ["", 51.0, 388.0, 439.0], ["", 90.0, 130.0, 220.0], ["", 469.0, 392.0, 861.0]], "column_names": ["a18_usual", "b18_none", "c18_male", "d18_female", "e18_both"]}