{"row_names": ["h62_in", "h63_in", "h64_hong", "h65_kowloon", "h66_new", "h67_other", "h68_no", "h69_work", "h70_places"], "meta": {"table_name": "Place of Work", "table_names": {"S": "\u5de5\u4f5c\u5730\u70b9", "E": "Place of Work", "T": "\u5de5\u4f5c\u5730\u9ede"}, "table_id": 15, "area": "N01"}, "data": [["", "", "", 951.0, 1129.0, 2080.0], ["", "", "", "", "", ""], ["", "", "", 729.0, 663.0, 1392.0], ["", "", "", 1271.0, 1394.0, 2665.0], ["", "", "", 1236.0, 934.0, 2170.0], ["", "", "", 397.0, 105.0, 502.0], ["", "", "", 484.0, 119.0, 603.0], ["", "", "", 16.0, 612.0, 628.0], ["", "", "", 767.0, 121.0, 888.0]], "column_names": ["h61_place", "i61_none", "j61_none", "k61_none", "l61_male", "m61_female", "n61_both"]}