{"row_names": ["a78_<", "a79_none", "a80_2000", "a81_none", "a82_4000", "a83_none", "a84_6000", "a85_none", "a86_8000", "a87_none", "a88_10000", "a89_none", "a90_15000", "a91_none", "a92_20000", "a93_none", "a94_25000", "a95_none", "a96_30000", "a97_none", "a98_40000", "a99_none", "a100_>=", "a101_none", "a102_unpaid", "a103_none"], "meta": {"table_name": "Monthly Income from Main Employment (HK$)", "table_names": {"S": "\u6bcf\u6708\u4e3b\u8981\u804c\u4e1a\u6536\u5165\uff08\u6e2f\u5143\uff09", "E": "Monthly Income from Main Employment (HK$)", "T": "\u6bcf\u6708\u4e3b\u8981\u8077\u696d\u6536\u5165\uff08\u6e2f\u5143\uff09"}, "table_id": 5, "area": "M27"}, "data": [["", 36.0, 77.0, 113.0], ["", 36.0, 77.0, 113.0], ["", 67.0, 1699.0, 1766.0], ["", 67.0, 51.0, 118.0], ["", 28.0, 302.0, 330.0], ["", 26.0, 130.0, 156.0], ["", 111.0, 119.0, 230.0], ["", 111.0, 119.0, 230.0], ["", 274.0, 176.0, 450.0], ["", 274.0, 171.0, 445.0], ["", 481.0, 450.0, 931.0], ["", 481.0, 450.0, 931.0], ["", 446.0, 323.0, 769.0], ["", 446.0, 323.0, 769.0], ["", 414.0, 559.0, 973.0], ["", 414.0, 559.0, 973.0], ["", 293.0, 242.0, 535.0], ["", 293.0, 242.0, 535.0], ["", 504.0, 311.0, 815.0], ["", 504.0, 311.0, 815.0], ["", 674.0, 520.0, 1194.0], ["", 674.0, 520.0, 1194.0], ["", 632.0, 331.0, 963.0], ["", 632.0, 331.0, 963.0], ["", 27.0, 37.0, 64.0], ["", 27.0, 37.0, 64.0]], "column_names": ["a77_main", "b77_none", "c77_male", "d77_female", "e77_both"]}