{"row_names": ["h62_in", "h63_in", "h64_hong", "h65_kowloon", "h66_new", "h67_other", "h68_no", "h69_work", "h70_places"], "meta": {"table_name": "Place of Work", "table_names": {"S": "\u5de5\u4f5c\u5730\u70b9", "E": "Place of Work", "T": "\u5de5\u4f5c\u5730\u9ede"}, "table_id": 15, "area": "N10"}, "data": [["", "", "", 380.0, 501.0, 881.0], ["", "", "", "", "", ""], ["", "", "", 641.0, 647.0, 1288.0], ["", "", "", 793.0, 511.0, 1304.0], ["", "", "", 839.0, 704.0, 1543.0], ["", "", "", 339.0, 171.0, 510.0], ["", "", "", 420.0, 78.0, 498.0], ["", "", "", 8.0, 367.0, 375.0], ["", "", "", 213.0, 81.0, 294.0]], "column_names": ["h61_place", "i61_none", "j61_none", "k61_none", "l61_male", "m61_female", "n61_both"]}