{"row_names": ["a62_working", "a63_employees", "a64_employers", "a65_self-employed", "a66_unpaid", "a67_persons", "a68_home-makers", "a69_students", "a70_retired", "a71_others"], "meta": {"table_name": "Economic Activity Status", "table_names": {"S": "\u7ecf\u6d4e\u6d3b\u52a8\u8eab\u5206", "E": "Economic Activity Status", "T": "\u7d93\u6fdf\u6d3b\u52d5\u8eab\u5206"}, "table_id": 4, "area": "E09"}, "data": [["", "", "", ""], ["", 2790.0, 2825.0, 5615.0], ["", 204.0, 79.0, 283.0], ["", 298.0, 127.0, 425.0], ["", 0.0, 3.0, 3.0], ["", "", "", ""], ["", 114.0, 840.0, 954.0], ["", 976.0, 842.0, 1818.0], ["", 935.0, 1125.0, 2060.0], ["", 822.0, 750.0, 1572.0]], "column_names": ["a61_economic", "b61_none", "c61_male", "d61_female", "e61_both"]}