{"row_names": ["h62_in", "h63_in", "h64_hong", "h65_kowloon", "h66_new", "h67_other", "h68_no", "h69_work", "h70_places"], "meta": {"table_name": "Place of Work", "table_names": {"S": "\u5de5\u4f5c\u5730\u70b9", "E": "Place of Work", "T": "\u5de5\u4f5c\u5730\u9ede"}, "table_id": 15, "area": "E09"}, "data": [["", "", "", 604.0, 1121.0, 1725.0], ["", "", "", "", "", ""], ["", "", "", 657.0, 581.0, 1238.0], ["", "", "", 663.0, 555.0, 1218.0], ["", "", "", 479.0, 233.0, 712.0], ["", "", "", 104.0, 40.0, 144.0], ["", "", "", 630.0, 223.0, 853.0], ["", "", "", 12.0, 230.0, 242.0], ["", "", "", 143.0, 51.0, 194.0]], "column_names": ["h61_place", "i61_none", "j61_none", "k61_none", "l61_male", "m61_female", "n61_both"]}