{"row_names": ["a62_working", "a63_employees", "a64_employers", "a65_self-employed", "a66_unpaid", "a67_persons", "a68_home-makers", "a69_students", "a70_retired", "a71_others"], "meta": {"table_name": "Economic Activity Status", "table_names": {"S": "\u7ecf\u6d4e\u6d3b\u52a8\u8eab\u5206", "E": "Economic Activity Status", "T": "\u7d93\u6fdf\u6d3b\u52d5\u8eab\u5206"}, "table_id": 4, "area": "E12"}, "data": [["", "", "", ""], ["", 4392.0, 4544.0, 8936.0], ["", 661.0, 175.0, 836.0], ["", 328.0, 225.0, 553.0], ["", 0.0, 0.0, 0.0], ["", "", "", ""], ["", 101.0, 1512.0, 1613.0], ["", 1586.0, 1480.0, 3066.0], ["", 1729.0, 1857.0, 3586.0], ["", 1425.0, 1254.0, 2679.0]], "column_names": ["a61_economic", "b61_none", "c61_male", "d61_female", "e61_both"]}